tracts/__init__.py
tracts/__itinerary/later.S.HTML
tracts/_licenses/gpl-3.0-standalone.html
tracts/_ops/_clique/__init__.py
tracts/_ops/_clique/group/__init__.py
tracts/_status/DB/records.json
tracts/_status/monitors/status_1.py
tracts/_status/status.proc.py
tracts/adventures/stack.S.HTML
tracts/license.S.HTML
tracts/mixer.MD
tracts/mixer.S.HTML
tracts-0.0.2.dist-info/METADATA
tracts-0.0.2.dist-info/WHEEL
tracts-0.0.2.dist-info/entry_points.txt
tracts-0.0.2.dist-info/RECORD
